eegrasp/__init__.py
eegrasp/eegrasp.py
eegrasp/graph.py
eegrasp/interpolate.py
eegrasp/utils.py
eegrasp/utils_examples.py
eegrasp/viz.py
eegrasp/tests/compare_distance_method.py
eegrasp/tests/compare_with_pygsp.py
eegrasp/tests/df_100.pkl
eegrasp/tests/df_pos.pkl
eegrasp/tests/load_from_mne.py
eegrasp-0.0.5.dist-info/METADATA
eegrasp-0.0.5.dist-info/WHEEL
eegrasp-0.0.5.dist-info/licenses/LICENSE
eegrasp-0.0.5.dist-info/RECORD
