Metadata-Version: 2.3
Name: EEGraSP
Version: 0.0.5
Summary: Package for EEG Graph signal Processing
Project-URL: Homepage, https://github.com/gsp-eeg/EEGraSP
Project-URL: Issues, https://github.com/gsp-eeg/EEGraSP/issues
Author-email: Julio Rodino <jrodino14@gmail.com>, Alejandro Weinstein <alejandro.weinstein@gmail.com>, Andres Herrera <herrerandresc@gmail.com>, Camilo Jara <camilo.jara@ug.uchile.cl>, Lucas Cortés <lucascortesg@gmail.com>
License-File: LICENSE
Classifier: License :: OSI Approved :: MIT License
Classifier: Operating System :: OS Independent
Classifier: Programming Language :: Python :: 3
Requires-Python: >=3.11
Requires-Dist: joblib
Requires-Dist: matplotlib
Requires-Dist: mne
Requires-Dist: numpy
Requires-Dist: pygsp2
Requires-Dist: scipy
Requires-Dist: tqdm
